buildout.cfg
setup.py
src/willdo/README.txt
src/willdo/__init__.py
src/willdo/app.py
src/willdo/configure.zcml
src/willdo/ftesting.zcml
src/willdo/interfaces.py
src/willdo/testing.py
src/willdo.egg-info/PKG-INFO
src/willdo.egg-info/SOURCES.txt
src/willdo.egg-info/dependency_links.txt
src/willdo.egg-info/entry_points.txt
src/willdo.egg-info/not-zip-safe
src/willdo.egg-info/requires.txt
src/willdo.egg-info/top_level.txt
src/willdo/app_templates/doittomorrowindex.pt
src/willdo/app_templates/willdoindex.pt
