Metadata-Version: 1.0
Name: willdo
Version: 0.2
Summary: Will Do List
Home-page: http://maurits.vanrees.org
Author: Maurits van Rees
Author-email: maurits@vanrees.org
License: GPL
Keywords: willdo todo
Platform: UNKNOWN
